{
  "dogs": [
    {
      "name": "Tillman",
      "image": "/assets/dalmation.png",
      "description": "Classical SUV Diesel bungle purple East vapid",
      "isFavorite": true,
      "id": 0
    },
    {
      "name": "Estefania",
      "image": "/assets/blue-heeler.png",
      "description": "evenly Bicycle male armor Officer Hybrid Fish",
      "isFavorite": true,
      "id": 1
    },
    {
      "name": "Zackery",
      "image": "/assets/blue-heeler.png",
      "description": "Hybrid Bedfordshire Investment Diesel navigating program Sweden",
      "isFavorite": true,
      "id": 2
    },
    {
      "name": "Keaton",
      "image": "/assets/blue-heeler.png",
      "description": "grow Wisconsin Virtual Latin Lamborghini Principal index scalable",
      "isFavorite": false,
      "id": 3
    },
    {
      "name": "Gianni",
      "image": "/assets/blue-heeler.png",
      "description": "Operations value Fish West up",
      "isFavorite": true,
      "id": 4
    },
    {
      "name": "Jamir",
      "image": "/assets/chihuahua.avif",
      "description": "Division Web Yemen female morph synthesize Southwest",
      "isFavorite": true,
      "id": 5
    },
    {
      "name": "Cara",
      "image": "/assets/chihuahua.avif",
      "description": "Southwest distributed Hybrid calculating National abaft transmit Ford",
      "isFavorite": true,
      "id": 6
    },
    {
      "name": "Glen",
      "image": "/assets/corgi.png",
      "description": "male Northeast Customer Consultant Birr female Producer",
      "isFavorite": true,
      "id": 7
    },
    {
      "name": "Eloise",
      "image": "/assets/dalmation.png",
      "description": "grey black redundant Designer Bespoke orange Danish",
      "isFavorite": true,
      "id": 8
    },
    {
      "name": "Dee",
      "image": "/assets/boxer.png",
      "description": "simplistic separately Tasty Centralized productize",
      "isFavorite": false,
      "id": 9
    },
    {
      "name": "Yolanda",
      "image": "/assets/corgi.png",
      "description": "Rutherfordium er Data that tan",
      "isFavorite": true,
      "id": 10
    },
    {
      "name": "Amalia",
      "image": "/assets/blue-heeler.png",
      "description": "Handcrafted Krona navigate Implementation Dirham Organized grey Southwest",
      "isFavorite": false,
      "id": 11
    },
    {
      "name": "Lolita",
      "image": "/assets/corgi.png",
      "description": "Granite Towels Touring virtual lime Chair transmitting",
      "isFavorite": false,
      "id": 12
    },
    {
      "name": "Kasandra",
      "image": "/assets/cowardly.png",
      "description": "Virtual green Visionary Ford haptic Northwest Wooden jealously",
      "isFavorite": true,
      "id": 13
    },
    {
      "name": "Mariana",
      "image": "/assets/boxer.png",
      "description": "optical Home East Associate Samoa non online Visionary",
      "isFavorite": false,
      "id": 14
    },
    {
      "name": "Tia",
      "image": "/assets/boxer.png",
      "description": "infantile why Bacon bypass joule",
      "isFavorite": true,
      "id": 15
    },
    {
      "name": "Buster",
      "image": "/assets/boxer.png",
      "description": "Money Square capacitor Borders Coupe sheepishly strategy",
      "isFavorite": true,
      "id": 16
    },
    {
      "name": "Cedrick",
      "image": "/assets/blue-heeler.png",
      "description": "Pants Alabama Magnesium laboriosam generating",
      "isFavorite": true,
      "id": 17
    },
    {
      "name": "Payton",
      "image": "/assets/blue-heeler.png",
      "description": "Gasoline Jazz male Aston Reggae East Electric firm",
      "isFavorite": true,
      "id": 18
    },
    {
      "name": "Anibal",
      "image": "/assets/corgi.png",
      "description": "Buckinghamshire Berkshire rudely Future Lithium Bike olive",
      "isFavorite": true,
      "id": 19
    },
    {
      "name": "asd",
      "description": "aDSSADF",
      "image": "/assets/chihuahua.avif",
      "id": 20
    },
    {
      "name": "asdf",
      "description": "asdf",
      "image": "/assets/dalmation.png",
      "id": 21
    },
    {
      "name": "asdf",
      "description": "asdf",
      "isFavorite": false,
      "image": "/assets/blue-heeler.png",
      "id": 22
    }
  ]
}